{"title":"重学线性代数","author":"朱维刚","cover":"https://static001.geekbang.org/resource/image/94/42/947e11727616df0f6427cba129a4a942.jpg","cid":327,"list":[{"id":265230,"title":"开篇词 | 从今天起，学会线性代数","chapter":"1569"},{"id":265757,"title":"01 | 导读：如何在机器学习中运用线性代数工具？","chapter":"1570"},{"id":265296,"title":"02 | 基本概念：线性代数研究的到底是什么问题？","chapter":"1570"},{"id":268296,"title":"03 | 矩阵：为什么说矩阵是线性方程组的另一种表达？","chapter":"1570"},{"id":269448,"title":"04 | 解线性方程组：为什么用矩阵求解的效率这么高？","chapter":"1570"},{"id":270329,"title":"05 | 线性空间：如何通过向量的结构化空间在机器学习中做降维处理？","chapter":"1570"},{"id":270884,"title":"06 | 线性无关：如何理解向量在N维空间的几何意义？","chapter":"1570"},{"id":271943,"title":"07 | 基和秩：为什么说它表达了向量空间中“有用”的向量个数？","chapter":"1570"},{"id":272815,"title":"08 | 线性映射：如何从坐标系角度理解两个向量空间之间的函数？","chapter":"1570"},{"id":274222,"title":"09 | 仿射空间：如何在图形的平移操作中大显身手？","chapter":"1570"},{"id":274958,"title":"10 | 解析几何：为什么说它是向量从抽象到具象的表达？","chapter":"1570"},{"id":275700,"title":"基础通关 | 线性代数5道典型例题及解析","chapter":"1570"},{"id":276274,"title":"11 | 如何运用线性代数方法解决图论问题？","chapter":"1608"},{"id":277606,"title":"12 | 如何通过矩阵转换让3D图形显示到二维屏幕上？","chapter":"1608"},{"id":278373,"title":"13 | 如何通过有限向量空间加持的希尔密码，提高密码被破译的难度？","chapter":"1608"},{"id":279476,"title":"14 | 如何在深度学习中运用数值代数的迭代法做训练？","chapter":"1608"},{"id":280657,"title":"15 | 如何从计算机的角度来理解线性代数？","chapter":"1608"},{"id":281200,"title":"强化通关 | 线性代数水平测试20题","chapter":"1608"},{"id":281646,"title":"结束语 | 和数学打交道这么多年，我的三点感悟","chapter":"1640"},{"id":265230,"title":"开篇词 | 从今天起，学会线性代数","chapter":"1569"},{"id":265757,"title":"01 | 导读：如何在机器学习中运用线性代数工具？","chapter":"1570"},{"id":265296,"title":"02 | 基本概念：线性代数研究的到底是什么问题？","chapter":"1570"},{"id":268296,"title":"03 | 矩阵：为什么说矩阵是线性方程组的另一种表达？","chapter":"1570"},{"id":269448,"title":"04 | 解线性方程组：为什么用矩阵求解的效率这么高？","chapter":"1570"},{"id":270329,"title":"05 | 线性空间：如何通过向量的结构化空间在机器学习中做降维处理？","chapter":"1570"},{"id":270884,"title":"06 | 线性无关：如何理解向量在N维空间的几何意义？","chapter":"1570"},{"id":271943,"title":"07 | 基和秩：为什么说它表达了向量空间中“有用”的向量个数？","chapter":"1570"},{"id":272815,"title":"08 | 线性映射：如何从坐标系角度理解两个向量空间之间的函数？","chapter":"1570"},{"id":274222,"title":"09 | 仿射空间：如何在图形的平移操作中大显身手？","chapter":"1570"},{"id":274958,"title":"10 | 解析几何：为什么说它是向量从抽象到具象的表达？","chapter":"1570"},{"id":275700,"title":"基础通关 | 线性代数5道典型例题及解析","chapter":"1570"},{"id":276274,"title":"11 | 如何运用线性代数方法解决图论问题？","chapter":"1608"},{"id":277606,"title":"12 | 如何通过矩阵转换让3D图形显示到二维屏幕上？","chapter":"1608"},{"id":278373,"title":"13 | 如何通过有限向量空间加持的希尔密码，提高密码被破译的难度？","chapter":"1608"},{"id":279476,"title":"14 | 如何在深度学习中运用数值代数的迭代法做训练？","chapter":"1608"},{"id":280657,"title":"15 | 如何从计算机的角度来理解线性代数？","chapter":"1608"},{"id":281200,"title":"强化通关 | 线性代数水平测试20题","chapter":"1608"},{"id":281646,"title":"结束语 | 和数学打交道这么多年，我的三点感悟","chapter":"1640"},{"id":265230,"title":"开篇词 | 从今天起，学会线性代数","chapter":"1569"},{"id":265757,"title":"01 | 导读：如何在机器学习中运用线性代数工具？","chapter":"1570"},{"id":265296,"title":"02 | 基本概念：线性代数研究的到底是什么问题？","chapter":"1570"},{"id":268296,"title":"03 | 矩阵：为什么说矩阵是线性方程组的另一种表达？","chapter":"1570"},{"id":269448,"title":"04 | 解线性方程组：为什么用矩阵求解的效率这么高？","chapter":"1570"},{"id":270329,"title":"05 | 线性空间：如何通过向量的结构化空间在机器学习中做降维处理？","chapter":"1570"},{"id":270884,"title":"06 | 线性无关：如何理解向量在N维空间的几何意义？","chapter":"1570"},{"id":271943,"title":"07 | 基和秩：为什么说它表达了向量空间中“有用”的向量个数？","chapter":"1570"},{"id":272815,"title":"08 | 线性映射：如何从坐标系角度理解两个向量空间之间的函数？","chapter":"1570"},{"id":274222,"title":"09 | 仿射空间：如何在图形的平移操作中大显身手？","chapter":"1570"},{"id":274958,"title":"10 | 解析几何：为什么说它是向量从抽象到具象的表达？","chapter":"1570"},{"id":275700,"title":"基础通关 | 线性代数5道典型例题及解析","chapter":"1570"},{"id":276274,"title":"11 | 如何运用线性代数方法解决图论问题？","chapter":"1608"},{"id":277606,"title":"12 | 如何通过矩阵转换让3D图形显示到二维屏幕上？","chapter":"1608"},{"id":278373,"title":"13 | 如何通过有限向量空间加持的希尔密码，提高密码被破译的难度？","chapter":"1608"},{"id":279476,"title":"14 | 如何在深度学习中运用数值代数的迭代法做训练？","chapter":"1608"},{"id":280657,"title":"15 | 如何从计算机的角度来理解线性代数？","chapter":"1608"},{"id":281200,"title":"强化通关 | 线性代数水平测试20题","chapter":"1608"},{"id":281646,"title":"结束语 | 和数学打交道这么多年，我的三点感悟","chapter":"1640"}]}